kkiapay/__init__.py
kkiapay/api.py
kkiapay/base.py
kkiapay/utils.py
tests/__init__.py
tests/context.py
tests/test_kkiapay.py
kkiapay-0.0.6.dist-info/METADATA
kkiapay-0.0.6.dist-info/WHEEL
kkiapay-0.0.6.dist-info/top_level.txt
kkiapay-0.0.6.dist-info/RECORD
