Metadata-Version: 2.1
Name: kkiapay
Version: 0.0.6
Summary: Community-driven Admin KkiaPay Sdk for Python
Home-page: https://github.com/PythonBenin/kkiapay-python
Author: Junior Gantin
Author-email: nioperas06@gmail.com
Classifier: Programming Language :: Python :: 3
Classifier: License :: OSI Approved :: MIT License
Classifier: Operating System :: OS Independent
